mcp_calculator_kel/__init__.py
mcp_calculator_kel/__main__.py
mcp_calculator_kel/server.py
open_server/__init__.py
open_server/__main__.py
open_server/open_platform_interface.py
open_server/server.py
open_server/sign_util.py
open_mcp_server-0.1.1.dist-info/METADATA
open_mcp_server-0.1.1.dist-info/WHEEL
open_mcp_server-0.1.1.dist-info/entry_points.txt
open_mcp_server-0.1.1.dist-info/top_level.txt
open_mcp_server-0.1.1.dist-info/RECORD
