Metadata-Version: 2.4
Name: open-mcp-server
Version: 0.1.1
Summary: Add your description here
Requires-Python: >=3.12
Requires-Dist: build>=1.3.0
Requires-Dist: fastmcp>=2.11.1
Requires-Dist: mcp[cli]>=1.12.3
Requires-Dist: twine>=6.1.0
